setup.cfg
setup.py
Terminal_Text_Color.egg-info/PKG-INFO
Terminal_Text_Color.egg-info/SOURCES.txt
Terminal_Text_Color.egg-info/dependency_links.txt
Terminal_Text_Color.egg-info/top_level.txt
terminal_text_color/__init__.py
terminal_text_color/alert_text_color.py
terminal_text_color/text_color.py