Metadata-Version: 1.1
Name: Terminal-Text-Color
Version: 0.3
Summary: Simple herramienta para darle color al texto en consola
Home-page: https://github.com/ElMijo/terminal-text-color-py
Author: Jerry Anselmi
Author-email: jerry.anselmi@gmail.com
License: MIT
Keywords: teminal,console,color,style,background,alert,elmijo
Platform: any
Classifier: Environment :: Console
Classifier: Intended Audience :: Developers
Classifier: License :: OSI Approved :: MIT License
Classifier: Natural Language :: Spanish
Classifier: Operating System :: Unix
Classifier: Programming Language :: Python :: 2.7
Classifier: Programming Language :: Python :: 3.2
Classifier: Programming Language :: Python :: 3.3
Classifier: Programming Language :: Python :: 3.4
Classifier: Intended Audience :: Developers
Classifier: Topic :: Software Development :: Libraries :: Python Modules
Classifier: Topic :: Software Development :: User Interfaces
Classifier: Topic :: Terminals :: Terminal Emulators/X Terminals
Classifier: Topic :: Utilities
